katcr/__init__.py
katcr/bot.py
katcr/engines/__init__.py
katcr/engines/base.py
katcr/engines/eztv.py
katcr/engines/jackett.py
katcr/engines/katcr.py
katcr/engines/nyaasi.py
katcr/engines/skytorrents.py
katcr/engines/tpb.py
katcr-3.0.7.dist-info/entry_points.txt
katcr-3.0.7.dist-info/LICENSE
katcr-3.0.7.dist-info/WHEEL
katcr-3.0.7.dist-info/METADATA
katcr-3.0.7.dist-info/RECORD
